whenwasi/__init__.py
whenwasi/__main__.py
whenwasi/py.typed
whenwasi-0.0.1a0.dist-info/entry_points.txt
whenwasi-0.0.1a0.dist-info/LICENSE
whenwasi-0.0.1a0.dist-info/WHEEL
whenwasi-0.0.1a0.dist-info/METADATA
whenwasi-0.0.1a0.dist-info/RECORD
