Metadata-Version: 2.1
Name: whenwasi
Version: 0.0.1a0
Summary: Whenwasi
Home-page: https://github.com/anschweitzer/whenwasi
License: MIT
Author: Andrew Schweitzer
Author-email: schweitz72@gmail.com
Requires-Python: >=3.7,<4.0
Classifier: Development Status :: 1 - Planning
Classifier: License :: OSI Approved :: MIT License
Classifier: Programming Language :: Python :: 3
Classifier: Programming Language :: Python :: 3.10
Classifier: Programming Language :: Python :: 3.7
Classifier: Programming Language :: Python :: 3.8
Classifier: Programming Language :: Python :: 3.9
Requires-Dist: click (>=8.0.1)
Project-URL: Changelog, https://github.com/anschweitzer/whenwasi/releases
Project-URL: Documentation, https://whenwasi.readthedocs.io
Project-URL: Repository, https://github.com/anschweitzer/whenwasi
